ayods/__init__.py
ayods/__main__.py
ayods/data.py
ayods/directory_handler.py
ayods/main.py
ayods/notebook.py
ayods/project.py
ayods/util.py
ayods/templates/Minimal.ipynb
ayods/templates/Professional.ipynb
ayods/templates/Standard.ipynb
ayods/templates/__init__.py
tests/__init__.py
ayods-0.1.dist-info/LICENSE
ayods-0.1.dist-info/METADATA
ayods-0.1.dist-info/WHEEL
ayods-0.1.dist-info/entry_points.txt
ayods-0.1.dist-info/top_level.txt
ayods-0.1.dist-info/RECORD
