Metadata-Version: 2.1
Name: ayods
Version: 0.1
Summary: Python CLI tool for initializing data science projects
Home-page: https://github.com/SandWithCheese/ayods
Author: Ahmad Naufal Ramadan
Author-email: naufalahmad022@gmail.com
License: MIT
Classifier: Programming Language :: Python :: 3.8
Classifier: License :: OSI Approved :: MIT License
Classifier: Operating System :: OS Independent
License-File: LICENSE
Requires-Dist: questionary ==2.1.0
